dony/.env.template
dony/__init__.py
dony/command.py
dony/find_repo_root.py
dony/shell.py
dony/prompts/__init__.py
dony/prompts/confirm.py
dony/prompts/echo.py
dony/prompts/error.py
dony/prompts/input.py
dony/prompts/press_any_key.py
dony/prompts/select.py
dony/prompts/select_many.py
dony/prompts/success.py
dony-0.6.0.dist-info/METADATA
dony-0.6.0.dist-info/WHEEL
dony-0.6.0.dist-info/licenses/LICENSE
dony-0.6.0.dist-info/RECORD
